azure/mgmt/azurestackhcivm/__init__.py
azure/mgmt/azurestackhcivm/_client.py
azure/mgmt/azurestackhcivm/_configuration.py
azure/mgmt/azurestackhcivm/_patch.py
azure/mgmt/azurestackhcivm/_validation.py
azure/mgmt/azurestackhcivm/_version.py
azure/mgmt/azurestackhcivm/py.typed
azure/mgmt/azurestackhcivm/_utils/__init__.py
azure/mgmt/azurestackhcivm/_utils/model_base.py
azure/mgmt/azurestackhcivm/_utils/serialization.py
azure/mgmt/azurestackhcivm/aio/__init__.py
azure/mgmt/azurestackhcivm/aio/_client.py
azure/mgmt/azurestackhcivm/aio/_configuration.py
azure/mgmt/azurestackhcivm/aio/_patch.py
azure/mgmt/azurestackhcivm/aio/operations/__init__.py
azure/mgmt/azurestackhcivm/aio/operations/_operations.py
azure/mgmt/azurestackhcivm/aio/operations/_patch.py
azure/mgmt/azurestackhcivm/models/__init__.py
azure/mgmt/azurestackhcivm/models/_enums.py
azure/mgmt/azurestackhcivm/models/_models.py
azure/mgmt/azurestackhcivm/models/_patch.py
azure/mgmt/azurestackhcivm/operations/__init__.py
azure/mgmt/azurestackhcivm/operations/_operations.py
azure/mgmt/azurestackhcivm/operations/_patch.py
azure_mgmt_azurestackhcivm-1.0.0b1.dist-info/licenses/LICENSE
azure_mgmt_azurestackhcivm-1.0.0b1.dist-info/METADATA
azure_mgmt_azurestackhcivm-1.0.0b1.dist-info/WHEEL
azure_mgmt_azurestackhcivm-1.0.0b1.dist-info/top_level.txt
azure_mgmt_azurestackhcivm-1.0.0b1.dist-info/RECORD
